src/__init__.py
src/__main__.py
src/main.py
src/api/__init__.py
src/api/clusters.py
src/api/dbfs.py
src/api/jobs.py
src/api/notebooks.py
src/api/sql.py
src/cli/__init__.py
src/cli/commands.py
src/core/__init__.py
src/core/auth.py
src/core/config.py
src/core/utils.py
src/server/__init__.py
src/server/__main__.py
src/server/app.py
src/server/databricks_mcp_server.py
iflow_mcp_databricks_mcp_server-0.1.1.dist-info/METADATA
iflow_mcp_databricks_mcp_server-0.1.1.dist-info/WHEEL
iflow_mcp_databricks_mcp_server-0.1.1.dist-info/entry_points.txt
iflow_mcp_databricks_mcp_server-0.1.1.dist-info/RECORD
