Metadata-Version: 2.4
Name: iflow-mcp_databricks-mcp-server
Version: 0.1.1
Summary: A Model Completion Protocol (MCP) server for Databricks
Author-email: MCP Server Team <example@example.com>
License: MIT
Classifier: License :: OSI Approved :: MIT License
Classifier: Operating System :: OS Independent
Classifier: Programming Language :: Python :: 3
Classifier: Programming Language :: Python :: 3.10
Classifier: Programming Language :: Python :: 3.11
Requires-Python: >=3.10
Requires-Dist: databricks-sdk
Requires-Dist: httpx
Requires-Dist: mcp[cli]>=1.2.0
Provides-Extra: cli
Requires-Dist: click; extra == 'cli'
Provides-Extra: dev
Requires-Dist: black; extra == 'dev'
Requires-Dist: pylint; extra == 'dev'
Requires-Dist: pytest; extra == 'dev'
Requires-Dist: pytest-asyncio; extra == 'dev'
